gemini_mcp/__init__.py
gemini_mcp/server.py
banana_mcp-1.0.4.dist-info/METADATA
banana_mcp-1.0.4.dist-info/WHEEL
banana_mcp-1.0.4.dist-info/entry_points.txt
banana_mcp-1.0.4.dist-info/licenses/LICENSE
banana_mcp-1.0.4.dist-info/RECORD
