Metadata-Version: 2.4
Name: banana-mcp
Version: 1.0.4
Summary: Banana MCP - Gemini 2.5 Flash image generation server
Project-URL: Homepage, https://github.com/yourusername/gemini-mcp
Project-URL: Documentation, https://github.com/yourusername/gemini-mcp#readme
Project-URL: Repository, https://github.com/yourusername/gemini-mcp.git
Project-URL: Bug Reports, https://github.com/yourusername/gemini-mcp/issues
Author-email: SuperHuang <superhuang@example.com>
License: MIT
License-File: LICENSE
Keywords: ai,gemini,image-generation,mcp,model-context-protocol
Classifier: Development Status :: 4 - Beta
Classifier: Intended Audience :: Developers
Classifier: License :: OSI Approved :: MIT License
Classifier: Programming Language :: Python :: 3
Classifier: Programming Language :: Python :: 3.8
Classifier: Programming Language :: Python :: 3.9
Classifier: Programming Language :: Python :: 3.10
Classifier: Programming Language :: Python :: 3.11
Classifier: Programming Language :: Python :: 3.12
Classifier: Topic :: Internet :: WWW/HTTP
Classifier: Topic :: Software Development :: Libraries :: Python Modules
Requires-Python: >=3.8
Requires-Dist: anyio>=3.0.0
Requires-Dist: httpx>=0.24.0
Requires-Dist: mcp>=1.0.0
